modbus_event_connect/__init__.py
modbus_event_connect/constants.py
modbus_event_connect/modbus_deviceadapter.py
modbus_event_connect/modbus_event_connect.py
modbus_event_connect/modbus_models.py
modbus_event_connect/micro_nabto/__init__.py
modbus_event_connect/micro_nabto/micro_nabto_connection.py
modbus_event_connect/micro_nabto/micro_nabto_event_connect.py
modbus_event_connect/micro_nabto/protocol/__init__.py
modbus_event_connect/micro_nabto/protocol/command_builder.py
modbus_event_connect/micro_nabto/protocol/packet.py
modbus_event_connect/micro_nabto/protocol/payload.py
modbus_event_connect/micro_nabto/protocol/payload_cp_id.py
modbus_event_connect/micro_nabto/protocol/payload_crypt.py
modbus_event_connect/micro_nabto/protocol/payload_ipx.py
modbus_event_connect/modbus_tcp/__init__.py
modbus_event_connect/modbus_tcp/modbus_tcp_event_connect.py
modbus_event_connect-0.1.8.dist-info/LICENSE
modbus_event_connect-0.1.8.dist-info/METADATA
modbus_event_connect-0.1.8.dist-info/WHEEL
modbus_event_connect-0.1.8.dist-info/top_level.txt
modbus_event_connect-0.1.8.dist-info/RECORD
