Metadata-Version: 2.1
Name: modbus_event_connect
Version: 0.1.8
Summary: A library designed for seamless interaction with Modbus devices using an event-driven approach, supporting TCP, unabto and other protocols.
Home-page: https://github.com/HairingX/modbus_event_connect
Author: HairingX
License: MIT
Keywords: modbus,unabto,micronabto,micro_nabto,modbustcp,modbus_tcp,event,remote,connect,library
Classifier: Development Status :: 3 - Alpha
Classifier: Programming Language :: Python :: 3.12
Classifier: Intended Audience :: Developers
Classifier: Topic :: Software Development :: Libraries
Classifier: License :: OSI Approved :: MIT License
Requires-Python: >=3.12
License-File: LICENSE
Requires-Dist: pyModbusTCP==0.3.0
